ExoRM/ExoRM.py
ExoRM/__init__.py
ExoRM/get_data.py
ExoRM/initialize_model.py
exorm-4.0.6.dist-info/METADATA
exorm-4.0.6.dist-info/WHEEL
exorm-4.0.6.dist-info/top_level.txt
exorm-4.0.6.dist-info/RECORD
